setup.py
nhs/__init__.py
nhs.egg-info/PKG-INFO
nhs.egg-info/SOURCES.txt
nhs.egg-info/dependency_links.txt
nhs.egg-info/top_level.txt